pyqtgen/__init__.py
pyqtgen/__main__.py
pyqtgen-0.0.1.dist-info/LICENSE
pyqtgen-0.0.1.dist-info/METADATA
pyqtgen-0.0.1.dist-info/WHEEL
pyqtgen-0.0.1.dist-info/entry_points.txt
pyqtgen-0.0.1.dist-info/top_level.txt
pyqtgen-0.0.1.dist-info/RECORD
