Metadata-Version: 2.2
Name: pyqtgen
Version: 0.0.1
Summary: Ninja file generator for PySide6
Home-page: https://github.com/mugiseyebrows/pyqtgen
Author: Stanislav Doronin
Author-email: mugisbrows@gmail.com
License-File: LICENSE
Dynamic: author
Dynamic: author-email
Dynamic: description
Dynamic: description-content-type
Dynamic: home-page
Dynamic: summary
